setup.py
pyfoursquare/__init__.py
pyfoursquare/foursquare.py
pyfoursquare/models.py
pyfoursquare/test_foursquare.py
pyfoursquare/utils.py
pyfoursquare.egg-info/PKG-INFO
pyfoursquare.egg-info/SOURCES.txt
pyfoursquare.egg-info/dependency_links.txt
pyfoursquare.egg-info/top_level.txt