Metadata-Version: 1.0
Name: pyfoursquare
Version: 0.0.14
Summary: Python Wrapper for Foursquare (http://foursquare.com/) API
Home-page: https://github.com/marcelcaraciolo/foursquare
Author: Marcel Caraciolo
Author-email: caraciol@gmail.com
License: MIT
Download-URL: https://github.com/marcelcaraciolo/foursquare/tarball/master
Keywords: foursquare library api
Platform: UNKNOWN
Classifier: Development Status :: 4 - Beta
Classifier: Topic :: Utilities
Classifier: Natural Language :: English
Classifier: Operating System :: OS Independent
Classifier: Programming Language :: Python :: 2
Classifier: Topic :: Internet
Classifier: Topic :: Internet :: WWW/HTTP
